chuyya_library/__init__.py
chuyya_library/my_library.py
chuyya_library/tests/__init__.py
chuyya_library/tests/test_my_library.py
chuyya_library-1.0.4.dist-info/LICENSE
chuyya_library-1.0.4.dist-info/METADATA
chuyya_library-1.0.4.dist-info/WHEEL
chuyya_library-1.0.4.dist-info/top_level.txt
chuyya_library-1.0.4.dist-info/RECORD
