Metadata-Version: 2.1
Name: chuyya_library
Version: 1.0.4
Summary: A Python library for generating shipment invoices in PDF
Home-page: https://github.com/your_username/my_library
Author: Siva Suriya Kandasamy
Author-email: kannanmahalsuriya@gmail.com
Project-URL: Bug Tracker, https://github.com/your_username/my_library/issues
Classifier: Programming Language :: Python :: 3
Classifier: License :: OSI Approved :: MIT License
Classifier: Operating System :: OS Independent
Requires-Python: >=3.6
License-File: LICENSE
Requires-Dist: fpdf
